pypassive-0.0.1.dist-info/METADATA
pypassive-0.0.1.dist-info/WHEEL
pypassive-0.0.1.dist-info/licenses/LICENSE.md
pypassive/__init__.py
pypassive/alqarawi_et_al_2021.py
pypassive/douglasdavis.py
pypassive/duncanmokwa_logspiral.py
pypassive/mokwaduncan_hyperbolic.py
pypassive/soil.py
pypassive/utility_functions.py
pypassive-0.0.1.dist-info/RECORD
