Metadata-Version: 2.1
Name: pypassive
Version: 0.0.1
Summary: A simple python package to compute p-y curve using log-spiral method and hyperbolic relationship.
Home-page: https://gitlab.com/geosharma/pypassive
Author-Email: Aashish Sharma <confusionaananda@gmail.com>
License: MIT
Project-URL: Homepage, https://gitlab.com/geosharma/pypassive
Project-URL: Repository, https://gitlab.com/geosharma/pypassive.git
Project-URL: Documentation, https://readthedocs.org/projects/pypassive/
Requires-Python: >=3.11
Requires-Dist: numpy>=1.26.2
Requires-Dist: scipy>=1.11.4
